tku_uart/src/const.v
// 4 вариант
`define Fclk        48000000 // 50000000    //50 MHz
`define BR          9600      //BAUDRATE - скорость 9.6 kBOD
`define Nt          `Fclk/`BR // 16'h1458 // 5208 //`Fclk/`BR   //50000000/9600
`define MY_ADR      16'h4900     //Базовый адрес
`define XCRC16      16'h4002     //CRC (x^16 + x^15 + x^2 + 1)
`define INIT_CRC    16'hFFFF   //Инициализация регистра CRC

tku_uart/src/my_block.v
`include "const.v"

module my_block (
    input clk,
    input ce_wr_dat,
    input [7:0] rx_dat,
    input [7:0] com,
    input [15:0] wr_adr,
    input [15:0] rd_adr,
    input [7:0] SW,
	 
	 output reg [15:0] DISPL = 16'h0000,
	 output reg [7:0] LED = 8'h00,
	 output wire [7:0] my_dat);

assign ew0 = wr_adr == `MY_ADR;
assign ew1 = wr_adr == `MY_ADR + 1;
assign ew2 = wr_adr == `MY_ADR + 2;

assign ce_wr_REG = (com == 8'h00) ? ce_wr_dat : 0;

assign er0 = rd_adr == `MY_ADR;
assign er1 = rd_adr == `MY_ADR + 1;
assign er2 = rd_adr == `MY_ADR + 2;
assign er3 = rd_adr == `MY_ADR + 3;

assign rd_my_MEM = (`MY_ADR <= rd_adr) & (rd_adr <= `MY_ADR+255);
assign wr_my_MEM = (`MY_ADR <= wr_adr) & (wr_adr <= `MY_ADR+255);
assign ce_wr_MEM = ((com == 8'h01) & wr_my_MEM) ? ce_wr_dat : 0;
assign my_dat = (com == 8'h80) ? dat_REG : ((com == 8'h81) & rd_my_MEM) ? dat_MEM : 8'h0;

wire [7:0] dat_MEM;
reg [7:0] dat_REG;

BMEM_256x8 mem(.clk(clk), .we(ce_wr_MEM), .DI(rx_dat), .Adr_wr(wr_adr[7:0]), .Adr_rd(rd_adr[7:0]),
    .DO(dat_MEM));

always @ (posedge clk) begin
    LED <= (ce_wr_REG & ew0) ? rx_dat : LED;
    DISPL[15:8] <= (ce_wr_REG & ew1) ? rx_dat : DISPL[15:8];
    DISPL[7:0] <= (ce_wr_REG & ew2) ? rx_dat : DISPL[7:0];
    dat_REG <= er0 ? LED : er1 ? DISPL[15:8] : er2 ? DISPL[7:0] : er3 ? SW : 8'h0;
end

endmodule


module BMEM_256x8 (
    input clk,      output reg [7:0]DO,
    input we,
    input [7:0] DI,
    input [7:0] Adr_wr,
    input [7:0] Adr_rd);

reg [7:0] MEM [255:0]; //блочная память 8 x 256 bit.

always @ (posedge clk) begin
    MEM[Adr_wr]<= we? DI :MEM[Adr_wr]; //Запись в память
    DO <= MEM[Adr_rd];
end

endmodule

tku_uart/src/testbench.v
`timescale 1 ns / 100 ps

module testbench();

reg clk = 1'b0;

always begin
    #10 clk = ~clk; /* Toggle clock every 10ns <=> 50MHz clock rate */
end

/* --- OUTPUT --- */
wire [15:0] DISPL;
wire [7:0] LED;
wire [7:0] my_dat;

/* --- INPUT --- */
reg ce_wr_dat = 0;
reg [7:0] rx_dat = 8'h00;
reg [7:0] rx_com = 8'h00;
reg [15:0] wr_adr = 16'h0000;
reg [15:0] rd_adr = 16'h0000;
reg [7:0] SW = 8'h00;

my_block my_block(.clk(clk), .ce_wr_dat(ce_wr_dat), .rx_dat(rx_dat), .com(rx_com), .wr_adr(wr_adr), .rd_adr(rd_adr), .SW(SW),
	.DISPL(DISPL), .LED(LED), .my_dat(my_dat));

// MY_ADR = 16'h4900
initial begin
    /* --- Writing test --- */
    #100
    ce_wr_dat = 1; rx_dat = 8'h11; rx_com = 8'h00; wr_adr = 16'h4900; // 11 => LED
    #100
    ce_wr_dat = 0;
    #100
    ce_wr_dat = 1; rx_dat = 8'h22; rx_com = 8'h00; wr_adr = 16'h4901; // 22 => DISPL[15:8]
    #100
    ce_wr_dat = 0;
    #100
    ce_wr_dat = 1; rx_dat = 8'h33; rx_com = 8'h00; wr_adr = 16'h4902; // 33 => DISPL[7:0]
    #100
    ce_wr_dat = 0;
    #100
    ce_wr_dat = 1; rx_dat = 8'hAA; rx_com = 8'h01; wr_adr = 16'h4900; // AA => MEM[00]
    #100
    ce_wr_dat = 0;
    #100
    ce_wr_dat = 1; rx_dat = 8'h44; rx_com = 8'h01; wr_adr = 16'h4903; // 44 => MEM[03]
    #100
    ce_wr_dat = 0;
    #100
    ce_wr_dat = 1; rx_dat = 8'h55; rx_com = 8'h01; wr_adr = 16'h4904; // 55 => MEM[04]
    #100
    ce_wr_dat = 0; rx_dat = 8'h00; wr_adr = 16'h0000;

    /* --- Reading test --- */
    #100
    rx_com = 8'h80; rd_adr = 16'h4900; // Read LED
    #100
    rx_com = 8'h80; rd_adr = 16'h4901; // Read DISPL[15:8]
    #100
    rx_com = 8'h80; rd_adr = 16'h4902; // Read DISPL[7:0]
    #100
    rx_com = 8'h80; rd_adr = 16'h4903; // Read SW
    #50
    SW = 16'hFF;
    #50
    rx_com = 8'h80; rd_adr = 16'h4903; // Read SW
    #100
    rx_com = 8'h81; rd_adr = 16'h4900; // Read MEM[00]
    #100
    rx_com = 8'h81; rd_adr = 16'h4901; // Read MEM[01]
    #100
    rx_com = 8'h81; rd_adr = 16'h4902; // Read MEM[02]
    #100
    rx_com = 8'h81; rd_adr = 16'h4903; // Read MEM[03]
    #100
    rx_com = 8'h81; rd_adr = 16'h4904; // Read MEM[04]
    #100
    rx_com = 8'h81; rd_adr = 16'h4905; // Read MEM[05]
end

initial begin
	$dumpvars;      /* Open for dump of signals */
	#300000
    //#20000000
    $finish;
end

endmodule

/*
com=8’h00 – загрузить байт в регистр,
com=8’h80 – прочитать регистр,
com=8’h01 – загрузить байт в память,
com=8’h81 – прочитать память.
*/

hex_display/src/hex_to_seg.v
module hex_to_seg (
	input [3:0]data,

	output reg [7:0]seg
);

always @(*) begin
	case(data)
		4'h0: seg = 8'b11111100;
		4'h1: seg = 8'b01100000;
		4'h2: seg = 8'b11011010;
		4'h3: seg = 8'b11110010;
		4'h4: seg = 8'b01100010;
		4'h5: seg = 8'b10110010;
		4'h6: seg = 8'b10111010;
		4'h7: seg = 8'b11100000;
		4'h8: seg = 8'b11111110;
		4'h9: seg = 8'b11110110;
		4'hA: seg = 8'b11101110;
		4'hB: seg = 8'b00111110;
		4'hC: seg = 8'b10011100;
		4'hD: seg = 8'b01111010;
		4'hE: seg = 8'b10011110;
		4'hF: seg = 8'b10001110;
	endcase
end

endmodule

tku_uart/src/hex_display.v
module hex_display (
	input clk,
	input [15:0]data,

	output [3:0]anodes,
	output [7:0]seg
);

reg [12:0]cnt;

always @(posedge clk) begin
	if(cnt == 5000)
		cnt <= 0;
	else
		cnt <= cnt + 1;
end

assign divided_clk = (cnt == 0);

reg [1:0]i = 2'h0;
wire [3:0]num = data[i * 4 +: 4];

assign anodes = (4'b1 << i);

hex_to_seg hex_to_seg(.data(num), .seg(seg));

always @(posedge divided_clk) begin
	i <= i + 1'h1;
end

endmodule

tku_uart/src/URXD_CRC_BL.v
`include "const.v"

module URXD_CRC_BL(
    input URXD,
    input clk,
	 
    output reg en_rx_byte=0,    //Интервал приема байта
    output reg en_rx_bl=0,      //Интервал приема блока байт
    output wire ok_rx_byte,     //Подтверждение приема байта
    output reg[7:0] cb_byte=0,  //Счетчик принятых байт
    output wire res,            //Сброс в конце паузы
    output reg[7:0] rx_lbl=0,      //Длина блока данных
    output reg [15:0] CRC=0,    //Контрольный код CRC
    output wire ce_wr_dat,      //Разрешение записи данных
    output reg[7:0] rx_dat=0,   //Принятый байт
    output reg[7:0] com=0,      //Команда
    output reg[15:0] wr_adr=0,  //Базовый адрес данных
    output wire ok_rx_bl,
	 output wire ce_bit);     //Конец приема блока байт

    parameter REF_PAUESE =10 ; //Допустимая пауза между байтами

//--------Приемник строки байт------------------------------
    reg [15:0] cb_tact = 0;  //Счетчик длительности такта (бита)
    wire ce_tact = (cb_tact==`Nt) ; //Tce_tact=1/BAUDRATE
    assign ce_bit = (cb_tact==(`Nt/2)); //Середина такта
    reg [3:0]cb_bit=0; //Счетчик бит в кадре UART
    reg [4:0]cb_res=0; //Счетчик паузы
    reg RXD=0, tRXD=0;
    assign res = (cb_res>=REF_PAUESE) & ce_tact & en_rx_bl ;
    wire com_wr = (com==8'h00) | (com==8'h01) ;
    wire com_rd = (com==8'h80) | (com==8'h81) ;

    //---Адреса регистров--------------------------
    wire T_com = (cb_byte==0); //Команда
    wire T_lbl = (cb_byte==1); //Длина блока
    wire T_Hb_adr = (cb_byte==2) ; //Старший байт адреса
    wire T_Lb_adr = (cb_byte==3) ; //Младший байт адреса
    wire T_dat = (cb_byte>3); //Интервал данных

    wire dRXD = !RXD & tRXD ; //"Спады" входного сигнала RXD
    assign ok_rx_byte = (ce_bit & (cb_bit==9) & en_rx_byte & tRXD); //Успешный прием байта
    wire st_rx_byte = dRXD & !en_rx_byte ; //Старт приема очередного байта
    wire st_rx_bl = dRXD & !en_rx_bl ; //Старт приема блока байт
    assign ok_rx_bl = res & (CRC==0);//Успешный прием блока байт (по паузе в 10 тактов между байтами)
    wire T_sh = (cb_bit<9) & (cb_bit>0); //Интервал данных байта
    wire x0 = CRC[0] ^ RXD;
    wire ce_crc = ce_bit & T_sh;
    reg[7:0] cb_wr_byte=0 ; //
    assign ce_wr_dat = T_dat & ok_rx_byte & com_wr & (cb_wr_byte<rx_lbl);

always @ (posedge clk) begin
    RXD <= URXD; // RXD - задержка URXD на такт
    tRXD <= RXD; // tRXD - задержка URXD на два такта
    cb_tact <= ((dRXD & !en_rx_byte) | ce_tact)? 1 : cb_tact+1;
    cb_bit <= (st_rx_byte | ((cb_bit==9) & ce_tact))? 0 : (ce_tact & en_rx_byte)? cb_bit+1 : cb_bit ;
    en_rx_byte <= (ce_bit & !RXD)? 1 : ((cb_bit==9) & ce_bit)? 0 : en_rx_byte;
    rx_dat <= (ce_bit & T_sh)? rx_dat>>1 | RXD<<7 : rx_dat ; //
    cb_byte <= ok_rx_bl? 0 : ok_rx_byte? cb_byte+1 : cb_byte ;
    cb_res <= en_rx_byte? 0 : (ce_tact)? cb_res+1 : cb_res ;// & en_rx_bl
    en_rx_bl <= st_rx_byte? 1 : ok_rx_bl? 0 : en_rx_bl ;
    CRC <= st_rx_bl? `INIT_CRC : (x0 & ce_crc)? (((CRC^`XCRC16)>>1) | 1<<15): ce_crc?
    (CRC>>1) : CRC ;//16'h4002
end

//---Загрузка регистров: команды и длиннны блока и адреса
always @ (posedge clk) begin
    com <= (T_com & ok_rx_byte)? rx_dat : com;
    rx_lbl <= (T_lbl & ok_rx_byte)? rx_dat : rx_lbl;

    cb_wr_byte <= (T_com & ok_rx_byte)? 0 :
    (T_lbl & com_rd & ok_rx_byte)? rx_dat :
    ce_wr_dat? cb_wr_byte+1 : cb_wr_byte;

    wr_adr[15:8] <= (T_Hb_adr & ok_rx_byte)? rx_dat :
    (T_dat & ce_wr_dat & (wr_adr[7:0]==8'hFF))? wr_adr[15:8]+1 : wr_adr[15:8] ;

    wr_adr[7:0] <= (T_Lb_adr & ok_rx_byte)? rx_dat :
    (T_dat & ce_wr_dat)? wr_adr[7:0]+1 : wr_adr[7:0] ;
end

endmodule

tku_uart/src/RET_TXD_CRC_BL.v
`include "const.v"
module RET_TXD_CRC_BL(
    input st,
    input clk,
    input [7:0] com,
    input [7:0] lbl,
    input [15:0] adr,
    input [7:0] dat,

    output reg[15:0] rd_adr=0,         //Адрес передаваемых байт данных
    output reg en_tx=0,                 //Интервал передачи блока байт
    output wire [7:0] tx_dat,           //Передаваемые байты
    output reg [15:0] CRC=16'hFFFF,     //Контрольный CRC код
    output reg [7:0] cb_byte=0,         //Счетчик передаваемых байт
    output wire UTXD);                   //Последовательные данные

    wire com_rd=(com==8'h80) | (com==8'h81); //Команда чтения
    wire com_wr=(com==8'h00) | (com==8'h01); //Команда записи

//------Передатчик блока байт-------------------------------------
    reg [15:0] cb_tact = 0; //Счетчик длительности такта (бита)
    wire ce_tact = (cb_tact==`Nt); //Tce_tact=1/BAUDRATE
    reg [3:0] cb_bit=0; //Счетчик бит байта
    reg [7:0] sr_dat=0 ; //Регистр сдвига бит байта
    wire T_start = ((cb_bit==0) & en_tx) ; //Интервал старт бита
    wire ce_sh=(cb_bit<9) & (cb_bit>0) & ce_tact; //Разрешение сдвига бит байта
    assign ce_stop = (cb_bit==9) & ce_tact ; //Импульс конца байта
    wire rep_st = st | (ce_stop & en_tx); //Импульсы запуска передачи байт
    assign UTXD = T_start? 0 :en_tx? sr_dat[0] : 1 ; //UTXD блока байт
    wire [7:0]N_byte = com_rd? lbl+4 : //com, lbl, Hb_adr, Lb_adr, dat0,dat1,....
    com_wr? 4 : //com, lbl, adr[15:8], adr[7:0]
    1; //com («чужая» команда)

    wire T_com = (cb_byte==0); // Интервал команды
    wire T_lbl = (cb_byte==1) ; // Интервал длинны блока
    wire T_Hb_adr = (cb_byte==2) ; // Интервал старшего байта адреса
    wire T_Lb_adr = (cb_byte==3) ; // Интервал младшего байта адреса
    wire T_Lb_CRC = (cb_byte==N_byte); // Интервал младшего байта CRC
    wire T_Hb_CRC = (cb_byte==N_byte+1); // Интервал старшего байта CRC

    wire ce_adr = (ce_stop & cb_byte>3) & !(T_Lb_CRC | T_Hb_CRC) ;

//--------Функциональное назначение байт ответа
    assign tx_dat= T_com? com : //Команда
    T_Lb_CRC? CRC[7:0] : //Младший байт CRC
    T_Hb_CRC? CRC[15:8] : //Старший байт CRC
    T_lbl? lbl : //Число байт данных
    T_Hb_adr? adr[15:8] : //Старший байт адреса
    T_Lb_adr? adr[ 7:0] : //Младший байт адреса :
    dat ; //Данные
    wire ce_crc = ce_sh& !(T_Lb_CRC | T_Hb_CRC);
    wire x0 = CRC[0] ^ sr_dat[0] ;

always @ (posedge clk) begin
    cb_tact <= (st | ce_tact)? 1 : cb_tact+1;
    cb_byte <= st? 0 : ce_stop? cb_byte+1 : cb_byte ;
    cb_bit <= rep_st? 0 : (ce_tact & en_tx)? cb_bit+1 : cb_bit ;
    sr_dat <= (T_start & ce_tact)? tx_dat : ce_sh? sr_dat>>1 | 1<<7 : sr_dat ;
    en_tx <= st? 1 : ((cb_byte==N_byte+1) & ce_stop)? 0 : en_tx ;
    rd_adr <= st? adr : ce_adr? rd_adr+1 : rd_adr ;
    //-- Вычисление CRC передатчика-------------------
    CRC <= st? `INIT_CRC : (x0 & ce_crc)? (((CRC^`XCRC16)>>1) | 1<<15): ce_crc? (CRC>>1) : CRC ;
end

endmodule

tku_uart/src/dump.vcd
$date
	Mon Mar 29 16:52:02 2021
$end
$version
	Icarus Verilog
$end
$timescale
	100ps
$end
$scope module RET_TXD_CRC_BL $end
$var wire 8 ! N_byte [7:0] $end
$var wire 1 " T_Hb_CRC $end
$var wire 1 # T_Hb_adr $end
$var wire 1 $ T_Lb_CRC $end
$var wire 1 % T_Lb_adr $end
$var wire 1 & T_com $end
$var wire 1 ' T_lbl $end
$var wire 1 ( T_start $end
$var wire 1 ) UTXD $end
$var wire 16 * adr [15:0] $end
$var wire 1 + ce_adr $end
$var wire 1 , ce_crc $end
$var wire 1 - ce_sh $end
$var wire 1 . ce_stop $end
$var wire 1 / ce_tact $end
$var wire 1 0 clk $end
$var wire 8 1 com [7:0] $end
$var wire 1 2 com_rd $end
$var wire 1 3 com_wr $end
$var wire 8 4 dat [7:0] $end
$var wire 8 5 lbl [7:0] $end
$var wire 1 6 rep_st $end
$var wire 1 7 st $end
$var wire 8 8 tx_dat [7:0] $end
$var wire 1 9 x0 $end
$var reg 16 : CRC [15:0] $end
$var reg 4 ; cb_bit [3:0] $end
$var reg 8 < cb_byte [7:0] $end
$var reg 16 = cb_tact [15:0] $end
$var reg 1 > en_tx $end
$var reg 16 ? rd_adr [15:0] $end
$var reg 8 @ sr_dat [7:0] $end
$upscope $end
$scope module URXD_CRC_BL $end
$var wire 1 A T_Hb_adr $end
$var wire 1 B T_Lb_adr $end
$var wire 1 C T_com $end
$var wire 1 D T_dat $end
$var wire 1 E T_lbl $end
$var wire 1 F T_sh $end
$var wire 1 G URXD $end
$var wire 1 H ce_bit $end
$var wire 1 I ce_crc $end
$var wire 1 J ce_tact $end
$var wire 1 K ce_wr_dat $end
$var wire 1 L clk $end
$var wire 1 M com_rd $end
$var wire 1 N com_wr $end
$var wire 1 O dRXD $end
$var wire 1 P ok_rx_bl $end
$var wire 1 Q ok_rx_byte $end
$var wire 1 R res $end
$var wire 1 S st_rx_bl $end
$var wire 1 T st_rx_byte $end
$var wire 1 U x0 $end
$var reg 16 V CRC [15:0] $end
$var reg 1 W RXD $end
$var reg 4 X cb_bit [3:0] $end
$var reg 8 Y cb_byte [7:0] $end
$var reg 5 Z cb_res [4:0] $end
$var reg 16 [ cb_tact [15:0] $end
$var reg 8 \ cb_wr_byte [7:0] $end
$var reg 8 ] com [7:0] $end
$var reg 1 ^ en_rx_bl $end
$var reg 1 _ en_rx_byte $end
$var reg 8 ` rx_dat [7:0] $end
$var reg 8 a rx_lbl [7:0] $end
$var reg 1 b tRXD $end
$var reg 16 c wr_adr [15:0] $end
$upscope $end
$scope module hex_display $end
$var wire 4 d anodes [3:0] $end
$var wire 1 e clk $end
$var wire 16 f data [15:0] $end
$var wire 1 g divided_clk $end
$var wire 4 h num [3:0] $end
$var wire 8 i seg [7:0] $end
$var reg 13 j cnt [12:0] $end
$var reg 2 k i [1:0] $end
$scope module hex_to_seg $end
$var wire 4 l data [3:0] $end
$var reg 8 m seg [7:0] $end
$upscope $end
$upscope $end
$scope module testbench $end
$var wire 16 n DISPL [15:0] $end
$var wire 8 o LED [7:0] $end
$var wire 8 p my_dat [7:0] $end
$var reg 8 q SW [7:0] $end
$var reg 1 r ce_wr_dat $end
$var reg 1 s clk $end
$var reg 16 t rd_adr [15:0] $end
$var reg 8 u rx_com [7:0] $end
$var reg 8 v rx_dat [7:0] $end
$var reg 16 w wr_adr [15:0] $end
$scope module my_block $end
$var wire 8 x SW [7:0] $end
$var wire 1 y ce_wr_MEM $end
$var wire 1 z ce_wr_REG $end
$var wire 1 { ce_wr_dat $end
$var wire 1 | clk $end
$var wire 8 } com [7:0] $end
$var wire 8 ~ dat_MEM [7:0] $end
$var wire 1 !" er0 $end
$var wire 1 "" er1 $end
$var wire 1 #" er2 $end
$var wire 1 $" er3 $end
$var wire 1 %" ew0 $end
$var wire 1 &" ew1 $end
$var wire 1 '" ew2 $end
$var wire 8 (" my_dat [7:0] $end
$var wire 16 )" rd_adr [15:0] $end
$var wire 1 *" rd_my_MEM $end
$var wire 8 +" rx_dat [7:0] $end
$var wire 16 ," wr_adr [15:0] $end
$var wire 1 -" wr_my_MEM $end
$var reg 16 ." DISPL [15:0] $end
$var reg 8 /" LED [7:0] $end
$var reg 8 0" dat_REG [7:0] $end
$scope module mem $end
$var wire 8 1" Adr_rd [7:0] $end
$var wire 8 2" Adr_wr [7:0] $end
$var wire 8 3" DI [7:0] $end
$var wire 1 | clk $end
$var wire 1 y we $end
$var reg 8 4" DO [7:0] $end
$upscope $end
$upscope $end
$upscope $end
$enddefinitions $end
#0
$dumpvars
bx 4"
b0 3"
b0 2"
b0 1"
bx 0"
b0 /"
b0 ."
0-"
b0 ,"
b0 +"
0*"
b0 )"
b0 ("
0'"
0&"
0%"
0$"
0#"
0""
0!"
bx ~
b0 }
0|
0{
0z
0y
b0 x
b0 w
b0 v
b0 u
b0 t
0s
0r
b0 q
b0 p
b0 o
b0 n
bx m
bz l
b0 k
bx j
bx i
bz h
xg
bz f
ze
b1 d
b0 c
0b
b0 a
b0 `
0_
0^
b0 ]
b0 \
b0 [
b0 Z
b0 Y
b0 X
0W
b0 V
0U
0T
0S
0R
0Q
0P
0O
1N
0M
zL
0K
0J
0I
0H
zG
0F
0E
0D
1C
0B
0A
b0 @
b0 ?
0>
b0 =
b0 <
b0 ;
b1111111111111111 :
19
bz 8
z7
x6
bz 5
bz 4
x3
x2
bz 1
z0
0/
0.
0-
0,
0+
bz *
1)
0(
0'
1&
0%
x$
0#
x"
bx !
$end
#100
b0 0"
b0 ."
1s
1|
#200
0s
0|
#300
b0 ."
1s
1|
#400
0s
0|
#500
b0 ."
1s
1|
#600
0s
0|
#700
b0 ."
1s
1|
#800
0s
0|
#900
b0 ."
1s
1|
#1000
1-"
1z
0s
0|
b100100100000000 w
b100100100000000 ,"
1%"
b10001 v
b10001 +"
b10001 3"
1r
1{
#1100
b0 ."
b10001 /"
b10001 o
1s
1|
#1200
0s
0|
#1300
b0 ."
1s
1|
#1400
0s
0|
#1500
b0 ."
1s
1|
#1600
0s
0|
#1700
b0 ."
1s
1|
#1800
0s
0|
#1900
b0 ."
1s
1|
#2000
0z
0s
0|
0r
0{
#2100
b0 ."
1s
1|
#2200
0s
0|
#2300
b0 ."
1s
1|
#2400
0s
0|
#2500
b0 ."
1s
1|
#2600
0s
0|
#2700
b0 ."
1s
1|
#2800
0s
0|
#2900
b0 ."
1s
1|
#3000
b1 2"
1z
0s
0|
b100100100000001 w
b100100100000001 ,"
0%"
1&"
b100010 v
b100010 +"
b100010 3"
1r
1{
#3100
b10001000000000 ."
b10001000000000 n
1s
1|
#3200
0s
0|
#3300
b10001000000000 ."
1s
1|
#3400
0s
0|
#3500
b10001000000000 ."
1s
1|
#3600
0s
0|
#3700
b10001000000000 ."
1s
1|
#3800
0s
0|
#3900
b10001000000000 ."
1s
1|
#4000
0z
0s
0|
0r
0{
#4100
b10001000000000 ."
1s
1|
#4200
0s
0|
#4300
b10001000000000 ."
1s
1|
#4400
0s
0|
#4500
b10001000000000 ."
1s
1|
#4600
0s
0|
#4700
b10001000000000 ."
1s
1|
#4800
0s
0|
#4900
b10001000000000 ."
1s
1|
#5000
b10 2"
1z
0s
0|
b100100100000010 w
b100100100000010 ,"
0&"
1'"
b110011 v
b110011 +"
b110011 3"
1r
1{
#5100
b10001000110011 n
b10001000110011 ."
1s
1|
#5200
0s
0|
#5300
b10001000110011 ."
1s
1|
#5400
0s
0|
#5500
b10001000110011 ."
1s
1|
#5600
0s
0|
#5700
b10001000110011 ."
1s
1|
#5800
0s
0|
#5900
b10001000110011 ."
1s
1|
#6000
0z
0s
0|
0r
0{
#6100
b10001000110011 ."
1s
1|
#6200
0s
0|
#6300
b10001000110011 ."
1s
1|
#6400
0s
0|
#6500
b10001000110011 ."
1s
1|
#6600
0s
0|
#6700
b10001000110011 ."
1s
1|
#6800
0s
0|
#6900
b10001000110011 ."
1s
1|
#7000
1y
b0 2"
0s
0|
b100100100000000 w
b100100100000000 ,"
1%"
0'"
b1 u
b1 }
b10101010 v
b10101010 +"
b10101010 3"
1r
1{
#7100
b10001000110011 ."
1s
1|
#7200
0s
0|
#7300
b10101010 4"
b10101010 ~
b10001000110011 ."
1s
1|
#7400
0s
0|
#7500
b10001000110011 ."
1s
1|
#7600
0s
0|
#7700
b10001000110011 ."
1s
1|
#7800
0s
0|
#7900
b10001000110011 ."
1s
1|
#8000
0y
0s
0|
0r
0{
#8100
b10001000110011 ."
1s
1|
#8200
0s
0|
#8300
b10001000110011 ."
1s
1|
#8400
0s
0|
#8500
b10001000110011 ."
1s
1|
#8600
0s
0|
#8700
b10001000110011 ."
1s
1|
#8800
0s
0|
#8900
b10001000110011 ."
1s
1|
#9000
b11 2"
1y
0s
0|
b100100100000011 w
b100100100000011 ,"
0%"
b1000100 v
b1000100 +"
b1000100 3"
1r
1{
#9100
b10001000110011 ."
1s
1|
#9200
0s
0|
#9300
b10001000110011 ."
1s
1|
#9400
0s
0|
#9500
b10001000110011 ."
1s
1|
#9600
0s
0|
#9700
b10001000110011 ."
1s
1|
#9800
0s
0|
#9900
b10001000110011 ."
1s
1|
#10000
0y
0s
0|
0r
0{
#10100
b10001000110011 ."
1s
1|
#10200
0s
0|
#10300
b10001000110011 ."
1s
1|
#10400
0s
0|
#10500
b10001000110011 ."
1s
1|
#10600
0s
0|
#10700
b10001000110011 ."
1s
1|
#10800
0s
0|
#10900
b10001000110011 ."
1s
1|
#11000
b100 2"
1y
0s
0|
b100100100000100 w
b100100100000100 ,"
b1010101 v
b1010101 +"
b1010101 3"
1r
1{
#11100
b10001000110011 ."
1s
1|
#11200
0s
0|
#11300
b10001000110011 ."
1s
1|
#11400
0s
0|
#11500
b10001000110011 ."
1s
1|
#11600
0s
0|
#11700
b10001000110011 ."
1s
1|
#11800
0s
0|
#11900
b10001000110011 ."
1s
1|
#12000
0-"
b0 2"
0y
0s
0|
b0 w
b0 ,"
b0 v
b0 +"
b0 3"
0r
0{
#12100
b10001000110011 ."
1s
1|
#12200
0s
0|
#12300
b10001000110011 ."
1s
1|
#12400
0s
0|
#12500
b10001000110011 ."
1s
1|
#12600
0s
0|
#12700
b10001000110011 ."
1s
1|
#12800
0s
0|
#12900
b10001000110011 ."
1s
1|
#13000
1*"
0s
0|
b100100100000000 t
b100100100000000 )"
1!"
b10000000 u
b10000000 }
#13100
b10001 p
b10001 ("
b10001 0"
b10001000110011 ."
1s
1|
#13200
0s
0|
#13300
b10001000110011 ."
1s
1|
#13400
0s
0|
#13500
b10001000110011 ."
1s
1|
#13600
0s
0|
#13700
b10001000110011 ."
1s
1|
#13800
0s
0|
#13900
b10001000110011 ."
1s
1|
#14000
b1 1"
0s
0|
b100100100000001 t
b100100100000001 )"
0!"
1""
#14100
b100010 p
b100010 ("
bx 4"
bx ~
b100010 0"
b10001000110011 ."
1s
1|
#14200
0s
0|
#14300
b10001000110011 ."
1s
1|
#14400
0s
0|
#14500
b10001000110011 ."
1s
1|
#14600
0s
0|
#14700
b10001000110011 ."
1s
1|
#14800
0s
0|
#14900
b10001000110011 ."
1s
1|
#15000
b10 1"
0s
0|
b100100100000010 t
b100100100000010 )"
0""
1#"
#15100
b110011 p
b110011 ("
b110011 0"
b10001000110011 ."
1s
1|
#15200
0s
0|
#15300
b10001000110011 ."
1s
1|
#15400
0s
0|
#15500
b10001000110011 ."
1s
1|
#15600
0s
0|
#15700
b10001000110011 ."
1s
1|
#15800
0s
0|
#15900
b10001000110011 ."
1s
1|
#16000
b11 1"
0s
0|
b100100100000011 t
b100100100000011 )"
0#"
1$"
#16100
b0 p
b0 ("
b1000100 4"
b1000100 ~
b0 0"
b10001000110011 ."
1s
1|
#16200
0s
0|
#16300
b10001000110011 ."
1s
1|
#16400
0s
0|
#16500
b11111111 p
b11111111 ("
b11111111 0"
b10001000110011 ."
1s
1|
b11111111 q
b11111111 x
#16600
0s
0|
#16700
b10001000110011 ."
1s
1|
#16800
0s
0|
#16900
b10001000110011 ."
1s
1|
#17000
0s
0|
#17100
b10001000110011 ."
1s
1|
#17200
0s
0|
#17300
b10001000110011 ."
1s
1|
#17400
0s
0|
#17500
b10001000110011 ."
1s
1|
#17600
0s
0|
#17700
b10001000110011 ."
1s
1|
#17800
0s
0|
#17900
b10001000110011 ."
1s
1|
#18000
b0 1"
b1000100 p
b1000100 ("
0s
0|
b100100100000000 t
b100100100000000 )"
1!"
0$"
b10000001 u
b10000001 }
#18100
b10101010 p
b10101010 ("
b10101010 4"
b10101010 ~
b10001 0"
b10001000110011 ."
1s
1|
#18200
0s
0|
#18300
b10001000110011 ."
1s
1|
#18400
0s
0|
#18500
b10001000110011 ."
1s
1|
#18600
0s
0|
#18700
b10001000110011 ."
1s
1|
#18800
0s
0|
#18900
b10001000110011 ."
1s
1|
#19000
b1 1"
0s
0|
b100100100000001 t
b100100100000001 )"
0!"
1""
#19100
bx p
bx ("
b100010 0"
b10001000110011 ."
bx 4"
bx ~
1s
1|
#19200
0s
0|
#19300
b10001000110011 ."
1s
1|
#19400
0s
0|
#19500
b10001000110011 ."
1s
1|
#19600
0s
0|
#19700
b10001000110011 ."
1s
1|
#19800
0s
0|
#19900
b10001000110011 ."
1s
1|
#20000
b10 1"
0s
0|
b100100100000010 t
b100100100000010 )"
0""
1#"
#20100
b110011 0"
b10001000110011 ."
1s
1|
#20200
0s
0|
#20300
b10001000110011 ."
1s
1|
#20400
0s
0|
#20500
b10001000110011 ."
1s
1|
#20600
0s
0|
#20700
b10001000110011 ."
1s
1|
#20800
0s
0|
#20900
b10001000110011 ."
1s
1|
#21000
b11 1"
0s
0|
b100100100000011 t
b100100100000011 )"
0#"
1$"
#21100
b1000100 p
b1000100 ("
b11111111 0"
b10001000110011 ."
b1000100 4"
b1000100 ~
1s
1|
#21200
0s
0|
#21300
b10001000110011 ."
1s
1|
#21400
0s
0|
#21500
b10001000110011 ."
1s
1|
#21600
0s
0|
#21700
b10001000110011 ."
1s
1|
#21800
0s
0|
#21900
b10001000110011 ."
1s
1|
#22000
b100 1"
0s
0|
b100100100000100 t
b100100100000100 )"
0$"
#22100
b1010101 p
b1010101 ("
b1010101 4"
b1010101 ~
b0 0"
b10001000110011 ."
1s
1|
#22200
0s
0|
#22300
b10001000110011 ."
1s
1|
#22400
0s
0|
#22500
b10001000110011 ."
1s
1|
#22600
0s
0|
#22700
b10001000110011 ."
1s
1|
#22800
0s
0|
#22900
b10001000110011 ."
1s
1|
#23000
b101 1"
0s
0|
b100100100000101 t
b100100100000101 )"
#23100
bx p
bx ("
b10001000110011 ."
bx 4"
bx ~
1s
1|
#23200
0s
0|
#23300
b10001000110011 ."
1s
1|
#23400
0s
0|
#23500
b10001000110011 ."
1s
1|
#23600
0s
0|
#23700
b10001000110011 ."
1s
1|
#23800
0s
0|
#23900
b10001000110011 ."
1s
1|
#24000
0s
0|
#24100
b10001000110011 ."
1s
1|
#24200
0s
0|
#24300
b10001000110011 ."
1s
1|
#24400
0s
0|
#24500
b10001000110011 ."
1s
1|
#24600
0s
0|
#24700
b10001000110011 ."
1s
1|
#24800
0s
0|
#24900
b10001000110011 ."
1s
1|
#25000
0s
0|
#25100
b10001000110011 ."
1s
1|
#25200
0s
0|
#25300
b10001000110011 ."
1s
1|
#25400
0s
0|
#25500
b10001000110011 ."
1s
1|
#25600
0s
0|
